colabcloud/__init__.py
colabcloud/colabcloud.py
colabcloud-0.0.1.dist-info/LICENSE
colabcloud-0.0.1.dist-info/METADATA
colabcloud-0.0.1.dist-info/WHEEL
colabcloud-0.0.1.dist-info/top_level.txt
colabcloud-0.0.1.dist-info/RECORD
